DEVELOPER.md
LICENSE
LICENSE-PycURL
LICENSE-cURL
MANIFEST.in
NOTICE
README.md
RELEASE-NOTES.md
setup.py
src/ez_setup.py
src/PycURLLibrary/__init__.py
src/PycURLLibrary/ctx.py
src/PycURLLibrary/url.py
src/PycURLLibrary/version.py
src/robotframework_pycurllibrary.egg-info/PKG-INFO
src/robotframework_pycurllibrary.egg-info/SOURCES.txt
src/robotframework_pycurllibrary.egg-info/dependency_links.txt
src/robotframework_pycurllibrary.egg-info/requires.txt
src/robotframework_pycurllibrary.egg-info/top_level.txt
test/testenv.py
test/testwebserver.py