Metadata-Version: 1.1
Name: robotframework-pycurllibrary
Version: 0.9.5
Summary: Robot Framework test library for client-side URL transfer
Home-page: https://github.com/jivalo/robotframework-pycurllibrary
Author: Markku Saarela
Author-email: ivalo@iki.fi
License: Apache License 2.0
Keywords: robotframework testing testautomation pycurl curl
Platform: any
Classifier: Development Status :: 4 - Beta
Classifier: License :: OSI Approved :: Apache Software License
Classifier: Operating System :: OS Independent
Classifier: Programming Language :: Python
Classifier: Topic :: Software Development :: Testing
